kokiy/__init__.py
kokiy/_mesh_utils.py
kokiy/_structured.py
kokiy/axishell.py
kokiy/cartshell.py
kokiy/cloudshell.py
kokiy/frustum_shell.py
kokiy/shell.py
kokiy/shell_2d.py
kokiy/shell_utils.py
kokiy/thickshell.py
kokiy/torch_shell.py
kokiy-0.5.0.dist-info/LICENSE.md
kokiy-0.5.0.dist-info/METADATA
kokiy-0.5.0.dist-info/WHEEL
kokiy-0.5.0.dist-info/top_level.txt
kokiy-0.5.0.dist-info/RECORD
