Metadata-Version: 2.1
Name: kokiy
Version: 0.5.0
Summary: Utilities to work on 2D and 3D structured grids
Home-page: https://gitlab.com/cerfacs/kokiy
Author: CoopTeam-CERFACS
Author-email: coop@cerfacs.com
License: UNKNOWN
Project-URL: Homepage, https://gitlab.com/cerfacs/kokiy
Project-URL: Documentation, https://kokiy.readthedocs.io/en/latest/
Project-URL: Bug Tracker, https://gitlab.com/cerfacs/kokiy/-/issues
Keywords: shell,mesh,scientific computing,finite elements,cfd
Platform: UNKNOWN
Classifier: Programming Language :: Python :: 3.7
Classifier: Programming Language :: Python :: 3.8
Classifier: Programming Language :: Python :: 3.9
Classifier: Programming Language :: Python :: 3.10
Classifier: License :: OSI Approved :: MIT License
Classifier: Topic :: Scientific/Engineering
Requires-Python: >=3.7
Provides-Extra: docs
Provides-Extra: tests
